tricot/__init__.py
tricot/command.py
tricot/condition.py
tricot/constants.py
tricot/docker.py
tricot/extractor.py
tricot/logging.py
tricot/main.py
tricot/plugin.py
tricot/resource.py
tricot/template.py
tricot/tricot.py
tricot/utils.py
tricot/validation.py
tricot-1.14.0.dist-info/METADATA
tricot-1.14.0.dist-info/WHEEL
tricot-1.14.0.dist-info/entry_points.txt
tricot-1.14.0.dist-info/licenses/LICENSE
tricot-1.14.0.dist-info/RECORD
