Metadata-Version: 2.4
Name: tricot
Version: 1.14.0
Summary: Trivial Command Testser
Project-URL: Homepage, https://github.com/qtc-de/tricot
Project-URL: Documentation, https://github.com/qtc-de/tricot/tree/main/docs
Project-URL: Repository, https://github.com/qtc-de/tricot
Project-URL: Bug Tracker, https://github.com/qtc-de/tricot/issues
Project-URL: Changelog, https://github.com/qtc-de/tricot/blob/main/CHANGELOG.md
Author: Tobias Neitzel (@qtc_de)
Maintainer: Tobias Neitzel (@qtc_de)
License:                     GNU GENERAL PUBLIC LICENSE
License-File: LICENSE
Keywords: end-to-end-testing,test-automation,testing,testing-framework,validation
Classifier: License :: OSI Approved :: GNU General Public License v3 (GPLv3)
Classifier: Operating System :: Unix
Classifier: Programming Language :: Python :: 3
Requires-Python: >=3.9
Requires-Dist: docker
Requires-Dist: pyyaml
Requires-Dist: termcolor
